{
  "gitSyncId": "6834436f15756d4a34e18dca_d8e89c8a-54df-447e-b19b-11fe944ccdb4",
  "id": "Applications Config_JSObject1.system_configprimaryColumnsEditActions1onSave",
  "pluginId": "js-plugin",
  "pluginType": "JS",
  "unpublishedAction": {
    "actionConfiguration": {
      "encodeParamsToggle": true,
      "jsArguments": [],
      "paginationType": "NONE",
      "timeoutInMillisecond": 10000
    },
    "clientSideExecution": true,
    "collectionId": "Applications Config_JSObject1",
    "confirmBeforeExecute": false,
    "datasource": {
      "isAutoGenerated": false,
      "name": "UNUSED_DATASOURCE",
      "pluginId": "js-plugin"
    },
    "dynamicBindingPathList": [
      {
        "key": "body"
      }
    ],
    "fullyQualifiedName": "JSObject1.system_configprimaryColumnsEditActions1onSave",
    "name": "system_configprimaryColumnsEditActions1onSave",
    "pageId": "Applications Config",
    "runBehaviour": "MANUAL",
    "userSetOnLoad": false
  }
}