{
  "gitSyncId": "6834436f15756d4a34e18dca_478602cb-eee8-41ba-9a45-fdccd818a750",
  "id": "Home_getTodayDate.getTodayDate",
  "pluginId": "js-plugin",
  "pluginType": "JS",
  "unpublishedAction": {
    "actionConfiguration": {
      "encodeParamsToggle": true,
      "jsArguments": [],
      "paginationType": "NONE",
      "timeoutInMillisecond": 10000
    },
    "collectionId": "Home_getTodayDate",
    "confirmBeforeExecute": false,
    "datasource": {
      "isAutoGenerated": false,
      "name": "UNUSED_DATASOURCE",
      "pluginId": "js-plugin"
    },
    "dynamicBindingPathList": [
      {
        "key": "body"
      }
    ],
    "fullyQualifiedName": "getTodayDate.getTodayDate",
    "name": "getTodayDate",
    "pageId": "Home",
    "runBehaviour": "ON_PAGE_LOAD",
    "userSetOnLoad": true
  }
}